README.rst
setup.py
ghost/__init__.py
ghost/api.py
ghost/constant.py
ghost/modle.py
ghost/util.py
ghost/demo/__init__.py
ghost/demo/demo.py
ghost/tests/__init__.py
ghost/tests/test_api.py
ghost_ts.egg-info/PKG-INFO
ghost_ts.egg-info/SOURCES.txt
ghost_ts.egg-info/dependency_links.txt
ghost_ts.egg-info/top_level.txt