Metadata-Version: 1.1
Name: ghost-ts
Version: 1.2.1
Summary: A framework for developing Quantitative Trading programmes
Home-page: http://www.shyouxia.cn
Author: admin
Author-email: admin@shyouxia.cn
License: MIT
Keywords: quant quantitative investment trading algotrading
Platform: UNKNOWN
Classifier: Operating System :: OS Independent
Classifier: Programming Language :: Python :: 3
Classifier: Topic :: Office/Business :: Financial :: Investment
Classifier: Programming Language :: Python :: Implementation :: CPython
Classifier: License :: OSI Approved :: MIT License
